{
  "baseUrl": "https://raw.githubusercontent.com/dhammanana/epitaka_downloads/refs/heads/main/dbs/parts/",
  "packages": {
    "epitaka": {
      "name": "Basic Database",
      "targetFile": "epitaka.db.gz",
      "totalSize": "167M",
      "parts": [
        { "filename": "epitaka.db.gz.part001", "sizeInBytes": 47185920 },
        { "filename": "epitaka.db.gz.part002", "sizeInBytes": 47185920 },
        { "filename": "epitaka.db.gz.part003", "sizeInBytes": 47185920 },
        { "filename": "epitaka.db.gz.part004", "sizeInBytes": 33554432 }
      ]
    },
    "nissaya": {
      "name": "Myanmar Nissaya",
      "targetFile": "nissaya.db.gz",
      "totalSize": "88.7M",
      "parts": [
        { "filename": "nissaya.db.gz.part001", "sizeInBytes": 47185920 },
        { "filename": "nissaya.db.gz.part002", "sizeInBytes": 45088768 },
        { "filename": "nissaya.db.gz.part003", "sizeInBytes": 684032 }
      ]
    },
    "epitaka_th": {
      "name": "Thai Translation",
      "targetFile": "epitaka_th.db.gz",
      "totalSize": "14M",
      "parts": [
        { "filename": "epitaka_th.db.gz.part001", "sizeInBytes": 14680064 }
      ]
    },
    "epitaka_en": {
      "name": "English Translation",
      "targetFile": "epitaka_en.db.gz",
      "totalSize": "37M",
      "parts": [
        { "filename": "epitaka_en.db.gz.part001", "sizeInBytes": 38797312 }
      ]
    },
    "epitaka_vi": {
      "name": "Vietnamese Translation",
      "targetFile": "epitaka_vi.db.gz",
      "totalSize": "37M",
      "parts": [
        { "filename": "epitaka_vi.db.gz.part001", "sizeInBytes": 47185920 },
        { "filename": "epitaka_vi.db.gz.part002", "sizeInBytes": 23112925 }
      ]
    }

  }
}
